nervels/__init__.py
nervels/compiler.py
nervels/document.py
nervels/nodes.py
nervels/parser.py
nervels/utils.py
nervels-1.0.2.dist-info/METADATA
nervels-1.0.2.dist-info/WHEEL
nervels-1.0.2.dist-info/top_level.txt
nervels-1.0.2.dist-info/RECORD
