Metadata-Version: 2.4
Name: nervels
Version: 1.0.2
Summary: NerveLS — a fast and extensible NLS (Nerve Logo Syntax) parser and compiler 
Author-email: CELESTIFYX Team <celestifyx@gmail.com>
License-Expression: GPL-3.0-or-later
Project-URL: Homepage, https://gitlab.com/nervefetch/nervels
Project-URL: Repository, https://gitlab.com/nervefetch/nervels
Project-URL: Issues, https://gitlab.com/nervefetch/nervels/-/issues
Keywords: nls,ascii,art,nervefetch,ansi,parser,compiler
Classifier: Programming Language :: Python :: 3.12
Classifier: Programming Language :: Python :: 3.13
Classifier: Topic :: Software Development :: Libraries :: Python Modules
Classifier: Topic :: Multimedia :: Graphics
Classifier: Operating System :: OS Independent
Requires-Python: >=3.12
Requires-Dist: chromakitx>=1.0.4
